pyJM/BasicFunctions.py
pyJM/__init__.py
pyJM/pyJM.py
pyJM/MuMax/MFM.py
pyJM/MuMax/__init__.py
pyJM/MuMax/mumax.py
pyJM/ThreeDimensional/Lamni.py
pyJM/ThreeDimensional/LamniMulti.py
pyJM/ThreeDimensional/__init__.py
pyJM-0.4.0.dist-info/AUTHORS.rst
pyJM-0.4.0.dist-info/LICENSE
pyJM-0.4.0.dist-info/METADATA
pyJM-0.4.0.dist-info/WHEEL
pyJM-0.4.0.dist-info/top_level.txt
pyJM-0.4.0.dist-info/RECORD
