Metadata-Version: 2.1
Name: pyJM
Version: 0.4.0
Summary: Package for analysis and visualisation of reconstructed three-dimensional magnetic imaging
Home-page: https://github.com/jmassey-17/pyJM
Author: Jamie Massey
Author-email: jamie435@hotmail.co.uk
License: GPLv3
Keywords: Data-Analysis Physics Image-Analysis
Classifier: Development Status :: 2 - Pre-Alpha
Classifier: Intended Audience :: Developers
Classifier: License :: OSI Approved :: GNU General Public License v3 (GPLv3)
Classifier: Natural Language :: English
Classifier: Programming Language :: Python :: 3
Classifier: Programming Language :: Python :: 3.6
Classifier: Programming Language :: Python :: 3.7
Classifier: Programming Language :: Python :: 3.8
Requires-Python: >=3.6
License-File: LICENSE
License-File: AUTHORS.rst
Requires-Dist: igor (==0.3)
Requires-Dist: matplotlib (>=3.4.3)
Requires-Dist: numpy (>=1.15.1)
Requires-Dist: pandas (>=1.3.4)
Requires-Dist: Pillow (>=8.4.0)
Requires-Dist: pytest (>=6.2.4)
Requires-Dist: pyvista (>=0.31.0)
Requires-Dist: scikit-image (>=0.18.3)
Requires-Dist: scipy (>=1.7.1)
Requires-Dist: seaborn (>=0.11.2)
Requires-Dist: setuptools (>=40.2.0)
Requires-Dist: Stoner (==0.10.4)
